biteopt.cpython-38-darwin.so
biteopt-0.2.3.dist-info/LICENSE
biteopt-0.2.3.dist-info/METADATA
biteopt-0.2.3.dist-info/WHEEL
biteopt-0.2.3.dist-info/top_level.txt
biteopt-0.2.3.dist-info/RECORD
