Metadata-Version: 2.1
Name: biteopt
Version: 0.2.3
Summary: Python Wrapper for Aleksey Vaneev's BiteOpt
Home-page: https://github.com/leonidk/biteopt
Author: leonidk
Author-email: lkeselman@gmail.com
License: UNKNOWN
Platform: UNKNOWN
